_chemfp.so
chemfp/rdmaccs2.patterns
chemfp/__init__.py
chemfp/bitops.py
chemfp/openbabel.py
chemfp/types.py
chemfp/substruct.patterns
chemfp/encodings.py
chemfp/slow.py
chemfp/openeye_patterns.py
chemfp/indigo.py
chemfp/fps_search.py
chemfp/arena.py
chemfp/fps_io.py
chemfp/rdkit.py
chemfp/openbabel_patterns.py
chemfp/indigo_patterns.py
chemfp/io.py
chemfp/pattern_fingerprinter.py
chemfp/argparse.py
chemfp/_compat.py
chemfp/sdf_reader.py
chemfp/openeye.py
chemfp/search.py
chemfp/rdkit_patterns.py
chemfp/rdmaccs.patterns
chemfp/progressbar/__init__.py
chemfp/progressbar/widgets.py
chemfp/progressbar/compat.py
chemfp/commandline/__init__.py
chemfp/commandline/oe2fps.py
chemfp/commandline/simsearch.py
chemfp/commandline/rdkit2fps.py
chemfp/commandline/sdf2fps.py
chemfp/commandline/ob2fps.py
chemfp/commandline/cmdsupport.py
chemfp/commandline/indigo2fps.py
chemfp/commandline/fpcat.py
chemfp/futures/__init__.py
chemfp/futures/_base.py
chemfp/futures/thread.py
chemfp/futures/_compat.py
chemfp/futures/process.py
chemfp-1.6.1.dist-info/WHEEL
chemfp-1.6.1.dist-info/COPYING
chemfp-1.6.1.dist-info/top_level.txt
chemfp-1.6.1.dist-info/METADATA
chemfp-1.6.1.dist-info/entry_points.txt
chemfp-1.6.1.dist-info/RECORD
