Metadata-Version: 2.1
Name: chemfp
Version: 1.6.1
Summary: Reference baseline for high-performance cheminformatics fingerprint search benchmarking
Home-page: http://chemfp.com/
Author: Andrew Dalke
Author-email: dalke@dalkescientific.com
License: MIT
Project-URL: Bug Tracker, https://todo.sr.ht/~dalke/chemfp
Project-URL: Documentation, https://chemfp.readthedocs.io/en/chemfp-1.6.1/
Project-URL: Changelog, https://chemfp.readthedocs.io/en/chemfp-1.6.1/#what-s-new-in-1-6-1
Platform: UNKNOWN
Classifier: Development Status :: 5 - Production/Stable
Classifier: Environment :: Console
Classifier: License :: OSI Approved :: MIT License
Classifier: Operating System :: Unix
Classifier: Programming Language :: Python :: 2.7
Classifier: Programming Language :: Python :: 2 :: Only
Classifier: Topic :: Scientific/Engineering :: Chemistry
Classifier: Topic :: Software Development :: Libraries :: Python Modules
Classifier: Intended Audience :: Science/Research
